{
  "group_tag": "keyboard",
  "origin_region": "TopLeft",
  "grouped_keys": [
    {
      "visualName": "",
      "tag": "ADDITIONALLIGHT1",
      "line_break": null,
      "margin_left": -47.0,
      "margin_top": -54.0,
      "width": 46.0,
      "height": 10.0,
      "font_size": 12.0,
      "enabled": true,
      "absolute_location": true,
      "image": ""
    },
    {
      "visualName": "",
      "tag": "ADDITIONALLIGHT2",
      "line_break": null,
      "margin_left": -1.0,
      "margin_top": -54.0,
      "width": 46.0,
      "height": 10.0,
      "font_size": 12.0,
      "enabled": true,
      "absolute_location": true,
      "image": ""
    },
    {
      "visualName": "",
      "tag": "ADDITIONALLIGHT3",
      "line_break": null,
      "margin_left": 45.0,
      "margin_top": -54.0,
      "width": 46.0,
      "height": 10.0,
      "font_size": 12.0,
      "enabled": true,
      "absolute_location": true,
      "image": ""
    },
    {
      "visualName": "",
      "tag": "ADDITIONALLIGHT4",
      "line_break": null,
      "margin_left": 91.0,
      "margin_top": -54.0,
      "width": 46.0,
      "height": 10.0,
      "font_size": 12.0,
      "enabled": true,
      "absolute_location": true,
      "image": ""
    },
    {
      "visualName": "",
      "tag": "ADDITIONALLIGHT5",
      "line_break": null,
      "margin_left": 137.0,
      "margin_top": -54.0,
      "width": 46.0,
      "height": 10.0,
      "font_size": 12.0,
      "enabled": true,
      "absolute_location": true,
      "image": ""
    },
    {
      "visualName": "",
      "tag": "ADDITIONALLIGHT6",
      "line_break": null,
      "margin_left": 183.0,
      "margin_top": -54.0,
      "width": 46.0,
      "height": 10.0,
      "font_size": 12.0,
      "enabled": true,
      "absolute_location": true,
      "image": ""
    },
    {
      "visualName": "",
      "tag": "ADDITIONALLIGHT7",
      "line_break": null,
      "margin_left": 229.0,
      "margin_top": -54.0,
      "width": 46.0,
      "height": 10.0,
      "font_size": 12.0,
      "enabled": true,
      "absolute_location": true,
      "image": ""
    },
    {
      "visualName": "",
      "tag": "ADDITIONALLIGHT8",
      "line_break": null,
      "margin_left": 275.0,
      "margin_top": -54.0,
      "width": 46.0,
      "height": 10.0,
      "font_size": 12.0,
      "enabled": true,
      "absolute_location": true,
      "image": ""
    },
    {
      "visualName": "",
      "tag": "ADDITIONALLIGHT9",
      "line_break": null,
      "margin_left": 321.0,
      "margin_top": -54.0,
      "width": 46.0,
      "height": 10.0,
      "font_size": 12.0,
      "enabled": true,
      "absolute_location": true,
      "image": ""
    },
    {
      "visualName": "",
      "tag": "ADDITIONALLIGHT10",
      "line_break": null,
      "margin_left": 367.0,
      "margin_top": -54.0,
      "width": 46.0,
      "height": 10.0,
      "font_size": 12.0,
      "enabled": true,
      "absolute_location": true,
      "image": ""
    },
    {
      "visualName": "",
      "tag": "ADDITIONALLIGHT11",
      "line_break": null,
      "margin_left": 413.0,
      "margin_top": -54.0,
      "width": 46.0,
      "height": 10.0,
      "font_size": 12.0,
      "enabled": true,
      "absolute_location": true,
      "image": ""
    },
    {
      "visualName": "",
      "tag": "ADDITIONALLIGHT12",
      "line_break": null,
      "margin_left": 459.0,
      "margin_top": -54.0,
      "width": 46.0,
      "height": 10.0,
      "font_size": 12.0,
      "enabled": true,
      "absolute_location": true,
      "image": ""
    },
    {
      "visualName": "",
      "tag": "ADDITIONALLIGHT13",
      "line_break": null,
      "margin_left": 505.0,
      "margin_top": -54.0,
      "width": 46.0,
      "height": 10.0,
      "font_size": 12.0,
      "enabled": true,
      "absolute_location": true,
      "image": ""
    },
    {
      "visualName": "",
      "tag": "ADDITIONALLIGHT14",
      "line_break": null,
      "margin_left": 551.0,
      "margin_top": -54.0,
      "width": 46.0,
      "height": 10.0,
      "font_size": 12.0,
      "enabled": true,
      "absolute_location": true,
      "image": ""
    },
    {
      "visualName": "",
      "tag": "ADDITIONALLIGHT15",
      "line_break": null,
      "margin_left": 597.0,
      "margin_top": -54.0,
      "width": 46.0,
      "height": 10.0,
      "font_size": 12.0,
      "enabled": true,
      "absolute_location": true,
      "image": ""
    },
    {
      "visualName": "",
      "tag": "ADDITIONALLIGHT16",
      "line_break": null,
      "margin_left": 643.0,
      "margin_top": -54.0,
      "width": 46.0,
      "height": 10.0,
      "font_size": 12.0,
      "enabled": true,
      "absolute_location": true,
      "image": ""
    },
    {
      "visualName": "",
      "tag": "ADDITIONALLIGHT17",
      "line_break": null,
      "margin_left": 689.0,
      "margin_top": -54.0,
      "width": 46.0,
      "height": 10.0,
      "font_size": 12.0,
      "enabled": true,
      "absolute_location": true,
      "image": ""
    },
    {
      "visualName": "",
      "tag": "ADDITIONALLIGHT18",
      "line_break": null,
      "margin_left": 735.0,
      "margin_top": -54.0,
      "width": 46.0,
      "height": 10.0,
      "font_size": 12.0,
      "enabled": true,
      "absolute_location": true,
      "image": ""
    },
    {
      "visualName": "",
      "tag": "ADDITIONALLIGHT19",
      "line_break": null,
      "margin_left": 781.0,
      "margin_top": -54.0,
      "width": 46.0,
      "height": 10.0,
      "font_size": 12.0,
      "enabled": true,
      "absolute_location": true,
      "image": ""
    },
    {
      "visualName": "LIGHTS",
      "tag": "BRIGHTNESS_SWITCH",
      "line_break": null,
      "margin_left": 104.0,
      "margin_top": -37.0,
      "width": 30.0,
      "height": 30.0,
      "font_size": 9.0,
      "enabled": true,
      "absolute_location": true,
      "image": ""
    },
    {
      "visualName": "LOCK",
      "tag": "LOCK_SWITCH",
      "line_break": null,
      "margin_left": 141.0,
      "margin_top": -37.0,
      "width": 30.0,
      "height": 30.0,
      "font_size": 9.0,
      "enabled": true,
      "absolute_location": true,
      "image": ""
    },
    {
      "visualName": "G1",
      "tag": "G1",
      "line_break": null,
      "margin_left": -43.0,
      "margin_top": 0.0,
      "width": 30.0,
      "height": 30.0,
      "font_size": 12.0,
      "enabled": true,
      "absolute_location": true,
      "image": ""
    },
    {
      "visualName": "G2",
      "tag": "G2",
      "line_break": null,
      "margin_left": -43.0,
      "margin_top": 37.0,
      "width": 30.0,
      "height": 30.0,
      "font_size": 12.0,
      "enabled": true,
      "absolute_location": true,
      "image": ""
    },
    {
      "visualName": "G3",
      "tag": "G3",
      "line_break": null,
      "margin_left": -43.0,
      "margin_top": 74.0,
      "width": 30.0,
      "height": 30.0,
      "font_size": 12.0,
      "enabled": true,
      "absolute_location": true,
      "image": ""
    },
    {
      "visualName": "G4",
      "tag": "G4",
      "line_break": null,
      "margin_left": -43.0,
      "margin_top": 111.0,
      "width": 30.0,
      "height": 30.0,
      "font_size": 12.0,
      "enabled": true,
      "absolute_location": true,
      "image": ""
    },
    {
      "visualName": "G5",
      "tag": "G5",
      "line_break": null,
      "margin_left": -43.0,
      "margin_top": 148.0,
      "width": 30.0,
      "height": 30.0,
      "font_size": 12.0,
      "enabled": true,
      "absolute_location": true,
      "image": ""
    },
    {
      "visualName": "G6",
      "tag": "G6",
      "line_break": null,
      "margin_left": -43.0,
      "margin_top": 185.0,
      "width": 30.0,
      "height": 30.0,
      "font_size": 12.0,
      "enabled": true,
      "absolute_location": true,
      "image": ""
    }
  ],
  "KeyText": {},
  "key_conversion": null,
  "Region": {
    "Location": {
      "IsEmpty": true,
      "X": 0.0,
      "Y": 0.0
    },
    "Size": "0, 0",
    "X": 0.0,
    "Y": 0.0,
    "Width": 0.0,
    "Height": 0.0,
    "Left": 0.0,
    "Top": 0.0,
    "Right": 0.0,
    "Bottom": 0.0,
    "IsEmpty": true
  }
}