{
  "group_tag": "mouse",
  "origin_region": "BottomRight",
  "grouped_keys": [
    {
      "visualName": "Mouse Logo",
      "tag": "Peripheral_Logo",
      "line_break": null,
      "margin_left": 90.0,
      "margin_top": -111.0,
      "width": 50.0,
      "height": 50.0,
      "font_size": null,
      "enabled": true,
      "absolute_location": true,
      "image": ""
    },
    {
      "visualName": "Scroll Wheel",
      "tag": "Peripheral_ScrollWheel",
      "line_break": null,
      "margin_left": 90.0,
      "margin_top": -171.0,
      "width": 50.0,
      "height": 50.0,
      "font_size": null,
      "enabled": true,
      "absolute_location": true,
      "image": ""
    },
    {
      "visualName": "",
      "tag": "MOUSEPADLIGHT1",
      "line_break": null,
      "margin_left": 15.0,
      "margin_top": -144.0,
      "width": 16.0,
      "height": 56.0,
      "font_size": null,
      "enabled": true,
      "absolute_location": true,
      "image": ""
    },
    {
      "visualName": "",
      "tag": "MOUSEPADLIGHT2",
      "line_break": null,
      "margin_left": 15.0,
      "margin_top": -88.0,
      "width": 16.0,
      "height": 56.0,
      "font_size": null,
      "enabled": true,
      "absolute_location": true,
      "image": ""
    },
    {
      "visualName": "",
      "tag": "MOUSEPADLIGHT3",
      "line_break": null,
      "margin_left": 31.5,
      "margin_top": -48.0,
      "width": 56.0,
      "height": 16.0,
      "font_size": null,
      "enabled": true,
      "absolute_location": true,
      "image": ""
    },
    {
      "visualName": "",
      "tag": "MOUSEPADLIGHT4",
      "line_break": null,
      "margin_left": 87.5,
      "margin_top": -48.0,
      "width": 56.0,
      "height": 16.0,
      "font_size": null,
      "enabled": true,
      "absolute_location": true,
      "image": ""
    },
    {
      "visualName": "",
      "tag": "MOUSEPADLIGHT5",
      "line_break": null,
      "margin_left": 143.5,
      "margin_top": -48.0,
      "width": 56.0,
      "height": 16.0,
      "font_size": null,
      "enabled": true,
      "absolute_location": true,
      "image": ""
    },
    {
      "visualName": "",
      "tag": "MOUSEPADLIGHT6",
      "line_break": null,
      "margin_left": 200.0,
      "margin_top": -88.0,
      "width": 16.0,
      "height": 56.0,
      "font_size": null,
      "enabled": true,
      "absolute_location": true,
      "image": ""
    },
    {
      "visualName": "",
      "tag": "MOUSEPADLIGHT7",
      "line_break": null,
      "margin_left": 200.0,
      "margin_top": -144.0,
      "width": 16.0,
      "height": 56.0,
      "font_size": null,
      "enabled": true,
      "absolute_location": true,
      "image": ""
    },
    {
      "visualName": "",
      "tag": "MOUSEPADLIGHT8",
      "line_break": null,
      "margin_left": 200.0,
      "margin_top": -200.0,
      "width": 16.0,
      "height": 56.0,
      "font_size": null,
      "enabled": true,
      "absolute_location": true,
      "image": ""
    },
    {
      "visualName": "",
      "tag": "MOUSEPADLIGHT9",
      "line_break": null,
      "margin_left": 143.5,
      "margin_top": -200.0,
      "width": 56.0,
      "height": 16.0,
      "font_size": null,
      "enabled": true,
      "absolute_location": true,
      "image": ""
    },
    {
      "visualName": "",
      "tag": "MOUSEPADLIGHT10",
      "line_break": null,
      "margin_left": 87.5,
      "margin_top": -200.0,
      "width": 56.0,
      "height": 16.0,
      "font_size": null,
      "enabled": true,
      "absolute_location": true,
      "image": ""
    },
    {
      "visualName": "",
      "tag": "MOUSEPADLIGHT11",
      "line_break": null,
      "margin_left": 31.5,
      "margin_top": -200.0,
      "width": 56.0,
      "height": 16.0,
      "font_size": null,
      "enabled": true,
      "absolute_location": true,
      "image": ""
    },
    {
      "visualName": "",
      "tag": "MOUSEPADLIGHT12",
      "line_break": null,
      "margin_left": 15.0,
      "margin_top": -200.0,
      "width": 16.0,
      "height": 56.0,
      "font_size": null,
      "enabled": true,
      "absolute_location": true,
      "image": ""
    }
  ],
  "KeyText": {},
  "key_conversion": null,
  "Region": {
    "Location": {
      "IsEmpty": true,
      "X": 0.0,
      "Y": 0.0
    },
    "Size": "0, 0",
    "X": 0.0,
    "Y": 0.0,
    "Width": 0.0,
    "Height": 0.0,
    "Left": 0.0,
    "Top": 0.0,
    "Right": 0.0,
    "Bottom": 0.0,
    "IsEmpty": true
  }
}